sumo_docker_pipeline/__init__.py
sumo_docker_pipeline/commons/__init__.py
sumo_docker_pipeline/commons/result_module.py
sumo_docker_pipeline/commons/sumo_config_obj.py
sumo_docker_pipeline/config_generation_module.py
sumo_docker_pipeline/logger_unit.py
sumo_docker_pipeline/operation_module/__init__.py
sumo_docker_pipeline/operation_module/base_operation.py
sumo_docker_pipeline/operation_module/docker_operation_module.py
sumo_docker_pipeline/operation_module/local_operation_module.py
sumo_docker_pipeline/pipeline.py
sumo_docker_pipeline/static.py
sumo_docker_pipeline-2.0.dist-info/LICENSE.txt
sumo_docker_pipeline-2.0.dist-info/WHEEL
sumo_docker_pipeline-2.0.dist-info/METADATA
sumo_docker_pipeline-2.0.dist-info/RECORD
