Metadata-Version: 2.1
Name: sumo-docker-pipeline
Version: 2.0
Summary: A pipeline to call a traffic simulator: SUMO
License: MIT
Author: Kensuke Mitsuzawa
Author-email: kensuke.mit@gmail.com
Maintainer: Kensuke Mitsuzawa
Maintainer-email: kensuke.mit@gmail.com
Requires-Python: >=3.7,<4.0
Classifier: License :: OSI Approved :: MIT License
Classifier: Programming Language :: Python :: 3
Classifier: Programming Language :: Python :: 3.7
Classifier: Programming Language :: Python :: 3.8
Classifier: Programming Language :: Python :: 3.9
Provides-Extra: full
Requires-Dist: Cartopy (>=0.18.0,<0.19.0)
Requires-Dist: Shapely (>=1.7.0,<2.0.0); extra == "full"
Requires-Dist: SumoNetVis (>=1.6.0,<2.0.0); extra == "full"
Requires-Dist: bs4
Requires-Dist: docker
Requires-Dist: geopandas (>=0.10.0,<0.11.0); extra == "full"
Requires-Dist: geoviews (>=1.9.1,<2.0.0); extra == "full"
Requires-Dist: joblib
Requires-Dist: lxml
Requires-Dist: pandas
Requires-Dist: pyproj (>=3.0.0,<4.0.0); extra == "full"
Requires-Dist: sumo-output-parsers (>=0.5,<0.6)
